color_palette/__init__.py
color_palette/color_palette.py
palette_gen-0.1.1.dist-info/LICENSE
palette_gen-0.1.1.dist-info/METADATA
palette_gen-0.1.1.dist-info/WHEEL
palette_gen-0.1.1.dist-info/entry_points.txt
palette_gen-0.1.1.dist-info/top_level.txt
palette_gen-0.1.1.dist-info/RECORD
