Metadata-Version: 2.1
Name: palette-gen
Version: 0.1.1
Summary: A simple tool to extract and display color palettes from images.
Home-page: https://github.com/auth-xyz/palette
Author: auth-xyz
Author-email: smmc.auth@gmail.com
Classifier: Programming Language :: Python :: 3
Classifier: License :: OSI Approved :: MIT License
Classifier: Operating System :: OS Independent
Requires-Python: >=3.6
License-File: LICENSE
Requires-Dist: Pillow
Requires-Dist: rich
Requires-Dist: scikit-learn
Requires-Dist: numpy
